scrabbler/__init__.py
scrabbler/scrabbler.py
scrabbler-0.3.0.dist-info/entry_points.txt
scrabbler-0.3.0.dist-info/WHEEL
scrabbler-0.3.0.dist-info/METADATA
scrabbler-0.3.0.dist-info/RECORD
